metorial_core/__init__.py
metorial_core/base.py
metorial_core/config.py
metorial_core/main.py
metorial_core/sdk.py
metorial_core/sdk_builder.py
metorial_core/session.py
metorial_core/tool_adapters.py
metorial_core/tool_manager.py
metorial_core/typed_endpoints.py
metorial_core/types.py
metorial_core/utils.py
metorial_core/adapters/__init__.py
metorial_core/adapters/anthropic.py
metorial_core/adapters/base.py
metorial_core/adapters/deepseek.py
metorial_core/adapters/factory.py
metorial_core/adapters/google.py
metorial_core/adapters/mistral.py
metorial_core/adapters/openai.py
metorial_core/adapters/openai_compatible.py
metorial_core/adapters/togetherai.py
metorial_core/adapters/xai.py
metorial_core/lib/__init__.py
metorial_core/lib/metrics.py
metorial_core/lib/safe_cleanup.py
metorial_core/lib/streaming.py
metorial_core/lib/clients/__init__.py
metorial_core/lib/clients/async_client.py
metorial_core/lib/clients/sync_client.py
metorial_core-1.0.12.dist-info/METADATA
metorial_core-1.0.12.dist-info/WHEEL
metorial_core-1.0.12.dist-info/licenses/LICENSE
metorial_core-1.0.12.dist-info/RECORD
